LICENSE
README.md
pyproject.toml
setup.py
sample_metadata/__init__.py
sample_metadata/api_client.py
sample_metadata/configuration.py
sample_metadata/exceptions.py
sample_metadata/model_utils.py
sample_metadata/rest.py
sample_metadata/api/__init__.py
sample_metadata/api/analysis_api.py
sample_metadata/api/family_api.py
sample_metadata/api/import_api.py
sample_metadata/api/participant_api.py
sample_metadata/api/project_api.py
sample_metadata/api/sample_api.py
sample_metadata/api/seqr_api.py
sample_metadata/api/sequence_api.py
sample_metadata/api/web_api.py
sample_metadata/apis/__init__.py
sample_metadata/model/__init__.py
sample_metadata/model/analysis_model.py
sample_metadata/model/analysis_query_model.py
sample_metadata/model/analysis_status.py
sample_metadata/model/analysis_type.py
sample_metadata/model/analysis_update_model.py
sample_metadata/model/body_get_latest_complete_analysis_for_type_post.py
sample_metadata/model/body_get_participants.py
sample_metadata/model/body_get_samples.py
sample_metadata/model/body_get_sequences_by_criteria.py
sample_metadata/model/export_type.py
sample_metadata/model/extra_participant_importer_handler.py
sample_metadata/model/family_update_model.py
sample_metadata/model/http_validation_error.py
sample_metadata/model/nested_family.py
sample_metadata/model/nested_participant.py
sample_metadata/model/nested_sample.py
sample_metadata/model/nested_sequence.py
sample_metadata/model/new_sample.py
sample_metadata/model/new_sequence.py
sample_metadata/model/paging_links.py
sample_metadata/model/participant_update_model.py
sample_metadata/model/participant_upsert.py
sample_metadata/model/participant_upsert_body.py
sample_metadata/model/project_row.py
sample_metadata/model/project_summary_response.py
sample_metadata/model/sample_batch_upsert.py
sample_metadata/model/sample_batch_upsert_body.py
sample_metadata/model/sample_type.py
sample_metadata/model/sample_update_model.py
sample_metadata/model/sequence_status.py
sample_metadata_ms.egg-info/PKG-INFO
sample_metadata_ms.egg-info/SOURCES.txt
sample_metadata_ms.egg-info/dependency_links.txt
sample_metadata_ms.egg-info/not-zip-safe
sample_metadata_ms.egg-info/requires.txt
sample_metadata_ms.egg-info/top_level.txt
